wboxkit/__init__.py
wboxkit/ciphers/__init__.py
wboxkit/ciphers/aes/__init__.py
wboxkit/ciphers/aes/aes.py
wboxkit/ciphers/aes/bitaes.py
wboxkit/ciphers/aes/keyschedule.py
wboxkit/ciphers/aes/linear.py
wboxkit/ciphers/aes/sbox.py
wboxkit/containers/__init__.py
wboxkit/containers/rect.py
wboxkit/containers/vector.py
wboxkit/fastcircuit.c
wboxkit/fastcircuit.h
wboxkit/fastcircuit.py
wboxkit/masking.py
wboxkit/prng.py
wboxkit/serialize.py
wboxkit/tracing.py
wboxkit-0.1.0.dist-info/WHEEL
wboxkit-0.1.0.dist-info/METADATA
wboxkit-0.1.0.dist-info/RECORD
