Metadata-Version: 2.1
Name: wboxkit
Version: 0.1.0
Summary: White-box Synthesis & Cryptanalysis Kit
Author: Aleksei Udovenko
Requires-Python: >=3.7,<4.0
Classifier: Programming Language :: Python :: 3
Classifier: Programming Language :: Python :: 3.10
Classifier: Programming Language :: Python :: 3.7
Classifier: Programming Language :: Python :: 3.8
Classifier: Programming Language :: Python :: 3.9
